Workbook

Sheet Inputs
A1: Parameter | B1: Unit | C1: Conservative | D1: Base | E1: Upside | F1: Source/rationale
A2: Pumps in fleet | B2: # | C2: 120 | D2: 120 | E2: 120 | F2: Client scenario
A3: Unplanned Failures per pump per year | B3: # | C3: 2 | D3: 2 | E3: 2 | F3: Assumption. The data pump failed about 17 times a year, which I treated as an outlier
A4: Repair cost at planned rates | B4: $ | C4: 8000 | D4: 8000 | E4: 8000 | F4: Illustrative: parts and labour
A5: Emergency premium | B5: x | C5: 1.75 | D5: 1.75 | E5: 1.75 | F5: Emergency callouts outside standard hours typically run at 1.5 to 2 times the standard labor rate.
A6: Secondary damage | B6: $ | C6: 6000 | D6: 6000 | E6: 6000 | F6: llustrative: seals, bearings and motor damage when a pump fails while running
A7: Hours out of service | B7: h | C7: 24 | D7: 24 | E7: 24 | F7: Illustrative
A8: Cost per hour out of service | B8: $ | C8: 300 | D8: 300 | E8: 300 | F8: Illustrative: running the standby pump, water tankering, SLA penalties
A9: Cost of caught failure, as % of unplanned one | B9: % | C9: 0.5 | D9: 0.4 | E9: 0.3 | F9: Model gives 2 hour notice, enough to switch to standby pumps
A10: Catch rate | B10: % | C10: 0.4 | D10: 0.5 | E10: 0.7 | F10: Model: 1 of 2 failures in the test period. The range reflects the small sample
A11: False alarms per pump per year | B11: # | C11: 30 | D11: 25 | E11: 12 | F11: Model: 4 in 59 days, about 25 a year
A12: Cost per false alarm | B12: $ | C12: 300 | D12: 250 | E12: 150 | F12: About 2 hours of engineer time with an occasional site visit
A13: Sensors and edge device per pump | B13: $ | C13: 2500 | D13: 2500 | E13: 2500 | F13: Illustrative
... A17: Discount rate | B17: % | C17: 0.1 | D17: 0.1 | E17: 0.1 | F17: Standard assumption

Sheet Calc
A1: LINE | B1: Unit | C1: Conservative | D1: Base | E1: Upside
A2: Failures per year | B2: # | C2: =Inputs!C2*Inputs!C3 -> 240 | D2: =Inputs!D2*Inputs!D3 -> 240 | E2: =Inputs!E2*Inputs!E3 -> 240
A3: Cost per unplanned failure | B3: $ | C3: =Inputs!C4*Inputs!C5+Inputs!C6+Inputs!C7*Inputs!C8 -> 27200 | D3: =Inputs!D4*Inputs!D5+Inputs!D6+Inputs!D7*Inputs!D8 -> 27200 | E3: =Inputs!E4*Inputs!E5+Inputs!E6+Inputs!E7*Inputs!E8 -> 27200
A4: Cost per caught failure | B4: $ | C4: =C3*Inputs!C9 -> 13600 | D4: =D3*Inputs!D9 -> 10880 | E4: =E3*Inputs!E9 -> 8160
A5: Annual cost today | B5: $ | C5: =MULTIPLY(C2,C3) -> 6528000 | D5: =MULTIPLY(D2,D3) -> 6528000 | E5: =MULTIPLY(E2,E3) -> 6528000
A6: Failures caught | B6: # | C6: =C2*Inputs!C10 -> 96 | D6: =D2*Inputs!D10 -> 120 | E6: =E2*Inputs!E10 -> 168
A7: Failures missed | B7: # | C7: =C2-C6 -> 144 | D7: =D2-D6 -> 120 | E7: =E2-E6 -> 72
A8: False alarms per year | B8: # | C8: =Inputs!C2*Inputs!C11 -> 3600 | D8: =Inputs!D2*Inputs!D11 -> 3000 | E8: =Inputs!E2*Inputs!E11 -> 1440
A9: Annual cost with predictive maintenance | B9: $ | C9: =C6*C4+C7*C3+C8*Inputs!C12 -> 6302400 | D9: =D6*D4+D7*D3+D8*Inputs!D12 -> 5319600 | E9: =E6*E4+E7*E3+E8*Inputs!E12 -> 3545280
A10: Gross savings | B10: $ | C10: =C5-C9 -> 225600 | D10: =D5-D9 -> 1208400 | E10: =E5-E9 -> 2982720
A11: Savings % | B11: % | C11: =C10/C5*100 -> 3.4558824 | D11: =D10/D5*100 -> 18.511029 | E11: =E10/E5*100 -> 45.691176
A12: Running cost | B12: $ | C12: =Inputs!C2*Inputs!C15+Inputs!C16 -> 102000 | D12: =Inputs!D2*Inputs!D15+Inputs!D16 -> 102000 | E12: =Inputs!E2*Inputs!E15+Inputs!E16 -> 102000
A13: Net annual benefit | B13: $ | C13: =C10-C12 -> 123600 | D13: =D10-D12 -> 1106400 | E13: =E10-E12 -> 2880720
A14: Upfront investment | B14: $ | C14: =Inputs!C2*Inputs!C13+Inputs!C14 -> 400000 | D14: =Inputs!D2*Inputs!D13+Inputs!D14 -> 400000 | E14: =Inputs!E2*Inputs!E13+Inputs!E14 -> 400000
A15: Payback (months) | B15: # | C15: =if(C13>0, C14/C13*12, "n/a") -> 38.834951 | D15: =if(D13>0, D14/D13*12, "n/a") -> 4.3383948 | E15: =if(E13>0, E14/E13*12, "n/a") -> 1.6662501
A16: 3-year NPV | B16: $ | C16: {=NPV(Inputs!C17,C13,C13,C13)-C14} -> -92625.094 | D16: {=NPV(Inputs!D17,D13,D13,D13)-D14} -> 2351453 | E16: {=NPV(Inputs!E17,E13,E13,E13)-E14} -> 6763924.3
A17: Break-even false-alarm cost | B17: $ | C17: =(C5-C6*C4-C7*C3-C12)/C8 -> 334.33333 | D17: =(D5-D6*D4-D7*D3-D12)/D8 -> 618.8 | E17: =(E5-E6*E4-E7*E3-E12)/E8 -> 2150.5

Sheet Sensitivity
A1: Driver | B1: Low | C1: High | D1: Net benefit at low | E1: Net benefit at high | F1: Swing | G1: Downside v/s base | H1: Upside v/s base
A2: Failures per pump/yr (1.5 – 3) | B2: 1.5 | C2: 3 | D2: =$B$11*B2*$B$13*$B$14*(1-$B$15)-$B$11*$B$16*$B$17-$B$18 -> 616800 | E2: =$B$11*C2*$B$13*$B$14*(1-$B$15)-$B$11*$B$16*$B$17-$B$18 -> 2085600 | F2: =E2-D2 -> 1468800 | G2: =D2-$B$19 -> -489600 | H2: =E2-$B$19 -> 979200
A3: Catch rate (40% – 70%) | B3: 0.4 | C3: 0.7 | D3: =$B$11*$B$12*$B$13*B3*(1-$B$15)-$B$11*$B$16*$B$17-$B$18 -> 714720 | E3: =$B$11*$B$12*$B$13*C3*(1-$B$15)-$B$11*$B$16*$B$17-$B$18 -> 1889760 | F3: =E3-D3 -> 1175040 | G3: =D3-$B$19 -> -391680 | H3: =E3-$B$19 -> 783360
A4: Cost per failure ($20k – $35k) | B4: 20000 | C4: 35000 | D4: =$B$11*$B$12*B4*$B$14*(1-$B$15)-$B$11*$B$16*$B$17-$B$18 -> 588000 | E4: =$B$11*$B$12*C4*$B$14*(1-$B$15)-$B$11*$B$16*$B$17-$B$18 -> 1668000 | F4: =E4-D4 -> 1080000 | G4: =D4-$B$19 -> -518400 | H4: =E4-$B$19 -> 561600
A5: False alarms per pump/yr (37 – 12) | B5: 37 | C5: 12 | D5: =$B$11*$B$12*$B$13*$B$14*(1-$B$15)-$B$11*B5*$B$17-$B$18 -> 746400 | E5: =$B$11*$B$12*$B$13*$B$14*(1-$B$15)-$B$11*C5*$B$17-$B$18 -> 1496400 | F5: =E5-D5 -> 750000 | G5: =D5-$B$19 -> -360000 | H5: =E5-$B$19 -> 390000
A6: Cost per false alarm ($400 – $150) | B6: 400 | C6: 150 | D6: =$B$11*$B$12*$B$13*$B$14*(1-$B$15)-$B$11*$B$16*B6-$B$18 -> 656400 | E6: =$B$11*$B$12*$B$13*$B$14*(1-$B$15)-$B$11*$B$16*C6-$B$18 -> 1406400 | F6: =E6-D6 -> 750000 | G6: =D6-$B$19 -> -450000 | H6: =E6-$B$19 -> 300000
A7: Caught failure cost (50% – 30%) | B7: 0.5 | C7: 0.3 | D7: =$B$11*$B$12*$B$13*$B$14*(1-B7)-$B$11*$B$16*$B$17-$B$18 -> 780000 | E7: =$B$11*$B$12*$B$13*$B$14*(1-C7)-$B$11*$B$16*$B$17-$B$18 -> 1432800 | F7: =E7-D7 -> 652800 | G7: =D7-$B$19 -> -326400 | H7: =E7-$B$19 -> 326400
A10: Base case inputs
A11: Pumps | B11: 120
A12: Failures per pump per year | B12: 2
A13: Cost per unplanned failure ($) | B13: 27200
A14: Catch rate | B14: 0.5
A15: Caught failure cost (% of unplanned) | B15: 0.4
A16: False alarms per pump per year | B16: 25
A17: Cost per false alarm ($) | B17: 250
A18: Running cost per year ($) | B18: 102000
A19: Base net benefit | B19: =B11*B12*B13*B14*(1-B15)-B11*B16*B17-B18 -> 1106400
